eldar_stringplus_matrix-0.1.0.dist-info/licenses/LICENSE
stringplus/__init__.py
eldar_stringplus_matrix-0.1.0.dist-info/METADATA
eldar_stringplus_matrix-0.1.0.dist-info/WHEEL
eldar_stringplus_matrix-0.1.0.dist-info/top_level.txt
eldar_stringplus_matrix-0.1.0.dist-info/RECORD
