Metadata-Version: 2.4
Name: eldar-stringplus-matrix
Version: 0.1.0
Summary: Python string methods extended library
Home-page: https://github.com/eldar/stringplus
Author: Eldar Eliyev
Author-email: your_email@example.com
Classifier: Programming Language :: Python :: 3
Classifier: License :: OSI Approved :: MIT License
Classifier: Operating System :: OS Independent
Requires-Python: >=3.8
License-File: LICENSE
Dynamic: author
Dynamic: author-email
Dynamic: classifier
Dynamic: description
Dynamic: description-content-type
Dynamic: home-page
Dynamic: license-file
Dynamic: requires-python
Dynamic: summary
